[
    {
        "id": -517526233769292866,
        "area": "Frontend",
        "tech": [
            "HTML",
            "CSS",
            "JavaScript ES7",
            "React",
            "Redux",
            "JQuery"
        ]
    },
    {
        "id": -9215662888573497568,
        "area": "Backend",
        "tech": [
            "Flask",
            "Django",
            "Express"
        ]
    },
    {
        "id": 5623133658532758795,
        "area": "Databases",
        "tech": [
            "MySQL",
            "PostgreSQL",
            "MongoDB",
            "Elasticsearch",
            "Redis"
        ]
    },
    {
        "id": 2185170609839343930,
        "area": "API",
        "tech": [
            "REST",
            " GraphQL"
        ]
    },
    {
        "id": -5118911185633406638,
        "area": "Data Science ",
        "tech": [
            "NumPy",
            "Pandas",
            "Matplotlib",
            "SciPy",
            "Jupyter"
        ]
    },
    {
        "id": 8912224509241424647,
        "area": "Programming Languages",
        "tech": [
            "Python",
            "TypeScript",
            "Swift"
        ]
    },
    {
        "id": 3452267385042263321,
        "area": "Machine Learning",
        "tech": [
            "Tensorflow",
            "PyTorch"
        ]
    },
    {
        "id": -8876727526089976127,
        "area": "Cloud",
        "tech": [
            "AWS",
            "CDK",
            "Docker"
        ]
    }
]